neuronunit/__init__.py
neuronunit/aibs.py
neuronunit/bbp.py
neuronunit/cellmodel.py
neuronunit/cellmodelp.py
neuronunit/get_glif_stim.py
neuronunit/get_three_features_from_allen_data.py
neuronunit/neuroelectro.py
neuronunit/neuromldb.py
neuronunit/plottools.py
neuronunit/capabilities/__init__.py
neuronunit/capabilities/channel.py
neuronunit/capabilities/spike_functions.py
neuronunit/models/__init__.py
neuronunit/models/bindings.py
neuronunit/models/channel.py
neuronunit/models/generic_network.py
neuronunit/models/lems.py
neuronunit/models/network_model.py
neuronunit/models/reduced.py
neuronunit/models/section_extension.py
neuronunit/models/static.py
neuronunit/models/very_reduced.py
neuronunit/models/very_reduced_sans_lems.py
neuronunit/models/backends/__init__.py
neuronunit/models/backends/__light_backends__.py
neuronunit/models/backends/badexp.py
neuronunit/models/backends/base.py
neuronunit/models/backends/bhh.py
neuronunit/models/backends/general_pyNN.py
neuronunit/models/backends/glif.py
neuronunit/models/backends/jNeuroML.py
neuronunit/models/backends/neuromldb.py
neuronunit/models/backends/neuron.py
neuronunit/models/backends/parse_glif.py
neuronunit/models/backends/rawpy.py
neuronunit/neuroconstruct/__init__.py
neuronunit/neuroconstruct/capabilities.py
neuronunit/neuroconstruct/models.py
neuronunit/optimisation/__init__.py
neuronunit/optimisation/algorithms.py
neuronunit/optimisation/data_transport_container.py
neuronunit/optimisation/dm_test_interoperable.py
neuronunit/optimisation/exhaustive_search.py
neuronunit/optimisation/get_neab.py
neuronunit/optimisation/get_three_feature_sets_from_nml_db.py
neuronunit/optimisation/get_three_features_from_allen_data.py
neuronunit/optimisation/model_parameters.py
neuronunit/optimisation/optimisations.py
neuronunit/optimisation/optimization_management.py
neuronunit/optimisation/results_analysis.py
neuronunit/tests/__init__.py
neuronunit/tests/allen_tests.py
neuronunit/tests/allen_tests_utils.py
neuronunit_opt-0.1.dist-info/METADATA
neuronunit_opt-0.1.dist-info/WHEEL
neuronunit_opt-0.1.dist-info/top_level.txt
neuronunit_opt-0.1.dist-info/RECORD
