Metadata-Version: 2.1
Name: neuronunit-opt
Version: 0.1
Summary: A SciUnit library for optimizing data-driven testing of single-neuron physiology models.
Home-page: http://github.com/russelljjarvis/NeuronunitOpt
Author: Russell Jarvis, Rick Gerkin
Author-email: rjjarvis@asu.edu
License: MIT
Platform: UNKNOWN
